jupyterlab_makefile_file_type_extension/__init__.py
jupyterlab_makefile_file_type_extension/_version.py
jupyterlab_makefile_file_type_extension-1.0.84.data/data/share/jupyter/labextensions/jupyterlab_makefile_file_type_extension/package.json
jupyterlab_makefile_file_type_extension-1.0.84.data/data/share/jupyter/labextensions/jupyterlab_makefile_file_type_extension/static/207.b143811fcad396f410d8.js
jupyterlab_makefile_file_type_extension-1.0.84.data/data/share/jupyter/labextensions/jupyterlab_makefile_file_type_extension/static/728.1918bf9a0180bf411ce7.js
jupyterlab_makefile_file_type_extension-1.0.84.data/data/share/jupyter/labextensions/jupyterlab_makefile_file_type_extension/static/remoteEntry.82c81b643717d691a3b9.js
jupyterlab_makefile_file_type_extension-1.0.84.data/data/share/jupyter/labextensions/jupyterlab_makefile_file_type_extension/static/style.js
jupyterlab_makefile_file_type_extension-1.0.84.data/data/share/jupyter/labextensions/jupyterlab_makefile_file_type_extension/static/third-party-licenses.json
jupyterlab_makefile_file_type_extension-1.0.84.data/data/share/jupyter/labextensions/jupyterlab_makefile_file_type_extension/install.json
jupyterlab_makefile_file_type_extension-1.0.84.dist-info/METADATA
jupyterlab_makefile_file_type_extension-1.0.84.dist-info/WHEEL
jupyterlab_makefile_file_type_extension-1.0.84.dist-info/licenses/LICENSE
jupyterlab_makefile_file_type_extension-1.0.84.dist-info/RECORD
